fast_header/__init__.py
fast_header/cache_control.py
fast_header/content_disposition.py
fast_header/content_range.py
fast_header/content_type.py
fast_header/etag.py
fast_header/helper.py
fast_header-0.1.3.dist-info/LICENSE
fast_header-0.1.3.dist-info/METADATA
fast_header-0.1.3.dist-info/WHEEL
fast_header-0.1.3.dist-info/RECORD
